[
    { "title": "Медикаментозная терапия (этиотропная и&nbsp;симптоматическая)" },
    { "title": "Гормональная коррекция и&nbsp;заместительная терапия" },
    { "title": "Противовоспалительное и&nbsp;антибактериальное лечение" },
    { "title": "Фармакологическая коррекция сексуальной функции" },
    { "title": "Лечение нарушений мочеиспускания" },
    { "title": "Комплексное ведение хронических урологических заболеваний" },
    { "title": "Сопровождение пациентов на&nbsp;гормональной и&nbsp;тестостероновой терапии" },
    { "title": "Индивидуальные схемы лечения с&nbsp;динамическим контролем" }
]
