[
    {
        "title": "Длительный кашель (более 8&nbsp;недель)"
    },
    {
        "title": "Одышка при физической нагрузке или в&nbsp;покое"
    },
    {
        "title": "Боли в&nbsp;грудной клетке при дыхании"
    },
    {
        "title": "Частые бронхиты или пневмонии"
    },
    {
        "title": "Снижение толерантности к&nbsp;физической нагрузке"
    },
    {
        "title": "Хрипы или свистящие звуки при дыхании"
    },
    {
        "title": "Выделение мокроты с&nbsp;примесью крови"
    },
    {
        "title": "Нарушения дыхания во&nbsp;сне"
    }
]
